[
  {
    "text": "应用案例",
    "start": 0,
    "end": 1717
  },
  {
    "text": "免模型案例：AlphaGo的走棋网络",
    "start": 1717,
    "end": 4581
  },
  {
    "text": "输入棋盘当前状态，直接评估落子位置价值",
    "start": 4581,
    "end": 8589
  },
  {
    "text": "优势是省去推演计算，每秒决策100多次",
    "start": 8589,
    "end": 12025
  },
  {
    "text": "有模型案例：特斯拉自动驾驶仿真",
    "start": 12025,
    "end": 14888
  },
  {
    "text": "物理引擎模拟雨天路滑，神经网络生成行人行为",
    "start": 14888,
    "end": 18896
  },
  {
    "text": "优势是零风险试错百亿次",
    "start": 18896,
    "end": 21760
  }
]